[
    {
        "name": "manufacturer_id",
        "dbType": "integer",
        "htmlType": "select",
        "validations": "required|exists:manufacturers,id",
        "searchable": false,
        "fillable": true,
        "primary": false,
        "inForm": true,
        "inIndex": true,
        "inView": true
    },
    {
        "name": "language_id",
        "dbType": "integer",
        "htmlType": "number",
        "validations": "required",
        "searchable": false,
        "fillable": true,
        "primary": false,
        "inForm": true,
        "inIndex": true,
        "inView": true
    },
    {
        "name": "name",
        "dbType": "string",
        "htmlType": "text",
        "validations": "required",
        "searchable": false,
        "fillable": true,
        "primary": false,
        "inForm": true,
        "inIndex": true,
        "inView": true
    },
    {
        "name": "description",
        "dbType": "text",
        "htmlType": "textarea",
        "validations": "",
        "searchable": false,
        "fillable": true,
        "primary": false,
        "inForm": true,
        "inIndex": true,
        "inView": true
    },
    {
        "name": "tag",
        "dbType": "string",
        "htmlType": "text",
        "validations": "required",
        "searchable": false,
        "fillable": true,
        "primary": false,
        "inForm": true,
        "inIndex": true,
        "inView": true
    }
]
